bip39gen/__init__.py
bip39gen/__main__.py
bip39gen/bip39-words.en.txt
bip39gen/bip39gen.py
bip39gen_nop-0.1.2.dist-info/LICENSE
bip39gen_nop-0.1.2.dist-info/METADATA
bip39gen_nop-0.1.2.dist-info/WHEEL
bip39gen_nop-0.1.2.dist-info/entry_points.txt
bip39gen_nop-0.1.2.dist-info/top_level.txt
bip39gen_nop-0.1.2.dist-info/RECORD
