Metadata-Version: 2.1
Name: bip39gen-nop
Version: 0.1.2
Summary: Generate random BIP-039 wordlists
Home-page: https://github.com/nopdotcom/bip39gen
Author: Jay Carlson
Author-email: nop@nop.com
License: MIT
Keywords: bip39 bip039
Platform: UNKNOWN
Classifier: Programming Language :: Python :: 3
Classifier: License :: OSI Approved :: MIT License
Classifier: Operating System :: OS Independent
